{
  "version": "3.4",
  "log": [
    {
      "@openzeppelin/contracts-upgradeable/access/OwnableUpgradeable.sol:OwnableUpgradeable": {
        "src": "@openzeppelin\\contracts-upgradeable\\access\\OwnableUpgradeable.sol:21",
        "inherit": [
          "@openzeppelin/contracts-upgradeable/utils/ContextUpgradeable.sol:ContextUpgradeable",
          "@openzeppelin/contracts-upgradeable/proxy/utils/Initializable.sol:Initializable"
        ],
        "libraries": [],
        "methods": [
          "owner()",
          "renounceOwnership()",
          "transferOwnership(address)"
        ],
        "linkReferences": [],
        "errors": [],
        "layout": {
          "storage": [],
          "types": {
            "t_address": {
              "label": "address",
              "numberOfBytes": "20"
            },
            "t_bool": {
              "label": "bool",
              "numberOfBytes": "1"
            },
            "t_struct(InitializableStorage)73_storage": {
              "label": "struct Initializable.InitializableStorage",
              "members": [
                {
                  "label": "_initialized",
                  "type": "t_uint64",
                  "offset": 0,
                  "slot": "0"
                },
                {
                  "label": "_initializing",
                  "type": "t_bool",
                  "offset": 8,
                  "slot": "0"
                }
              ],
              "numberOfBytes": "32"
            },
            "t_struct(OwnableStorage)13_storage": {
              "label": "struct OwnableUpgradeable.OwnableStorage",
              "members": [
                {
                  "label": "_owner",
                  "type": "t_address",
                  "offset": 0,
                  "slot": "0"
                }
              ],
              "numberOfBytes": "32"
            },
            "t_uint64": {
              "label": "uint64",
              "numberOfBytes": "8"
            }
          },
          "layoutVersion": "1.2",
          "flat": false,
          "namespaces": {
            "erc7201:openzeppelin.storage.Ownable": [
              {
                "contract": "OwnableUpgradeable",
                "label": "_owner",
                "type": "t_address",
                "src": "@openzeppelin\\contracts-upgradeable\\access\\OwnableUpgradeable.sol:24",
                "offset": 0,
                "slot": "0"
              }
            ],
            "erc7201:openzeppelin.storage.Initializable": [
              {
                "contract": "Initializable",
                "label": "_initialized",
                "type": "t_uint64",
                "src": "@openzeppelin\\contracts-upgradeable\\proxy\\utils\\Initializable.sol:69",
                "offset": 0,
                "slot": "0"
              },
              {
                "contract": "Initializable",
                "label": "_initializing",
                "type": "t_bool",
                "src": "@openzeppelin\\contracts-upgradeable\\proxy\\utils\\Initializable.sol:73",
                "offset": 8,
                "slot": "0"
              }
            ]
          }
        },
        "solcVersion": "0.8.28"
      },
      "@openzeppelin/contracts-upgradeable/proxy/utils/Initializable.sol:Initializable": {
        "src": "@openzeppelin\\contracts-upgradeable\\proxy\\utils\\Initializable.sol:56",
        "inherit": [],
        "libraries": [],
        "methods": [],
        "linkReferences": [],
        "errors": [],
        "layout": {
          "storage": [],
          "types": {
            "t_bool": {
              "label": "bool",
              "numberOfBytes": "1"
            },
            "t_struct(InitializableStorage)73_storage": {
              "label": "struct Initializable.InitializableStorage",
              "members": [
                {
                  "label": "_initialized",
                  "type": "t_uint64",
                  "offset": 0,
                  "slot": "0"
                },
                {
                  "label": "_initializing",
                  "type": "t_bool",
                  "offset": 8,
                  "slot": "0"
                }
              ],
              "numberOfBytes": "32"
            },
            "t_uint64": {
              "label": "uint64",
              "numberOfBytes": "8"
            }
          },
          "layoutVersion": "1.2",
          "flat": false,
          "namespaces": {
            "erc7201:openzeppelin.storage.Initializable": [
              {
                "contract": "Initializable",
                "label": "_initialized",
                "type": "t_uint64",
                "src": "@openzeppelin\\contracts-upgradeable\\proxy\\utils\\Initializable.sol:69",
                "offset": 0,
                "slot": "0"
              },
              {
                "contract": "Initializable",
                "label": "_initializing",
                "type": "t_bool",
                "src": "@openzeppelin\\contracts-upgradeable\\proxy\\utils\\Initializable.sol:73",
                "offset": 8,
                "slot": "0"
              }
            ]
          }
        },
        "solcVersion": "0.8.28"
      },
      "@openzeppelin/contracts-upgradeable/proxy/utils/UUPSUpgradeable.sol:UUPSUpgradeable": {
        "src": "@openzeppelin\\contracts-upgradeable\\proxy\\utils\\UUPSUpgradeable.sol:20",
        "inherit": [
          "@openzeppelin/contracts/interfaces/draft-IERC1822.sol:IERC1822Proxiable",
          "@openzeppelin/contracts-upgradeable/proxy/utils/Initializable.sol:Initializable"
        ],
        "libraries": [
          "@openzeppelin/contracts/proxy/ERC1967/ERC1967Utils.sol:ERC1967Utils"
        ],
        "methods": [
          "proxiableUUID()",
          "upgradeToAndCall(address,bytes)"
        ],
        "linkReferences": [],
        "errors": [
          {
            "kind": "delegatecall",
            "src": "@openzeppelin\\contracts\\utils\\Address.sol:97"
          }
        ],
        "layout": {
          "storage": [],
          "types": {
            "t_bool": {
              "label": "bool",
              "numberOfBytes": "1"
            },
            "t_struct(InitializableStorage)73_storage": {
              "label": "struct Initializable.InitializableStorage",
              "members": [
                {
                  "label": "_initialized",
                  "type": "t_uint64",
                  "offset": 0,
                  "slot": "0"
                },
                {
                  "label": "_initializing",
                  "type": "t_bool",
                  "offset": 8,
                  "slot": "0"
                }
              ],
              "numberOfBytes": "32"
            },
            "t_uint64": {
              "label": "uint64",
              "numberOfBytes": "8"
            }
          },
          "layoutVersion": "1.2",
          "flat": false,
          "namespaces": {
            "erc7201:openzeppelin.storage.Initializable": [
              {
                "contract": "Initializable",
                "label": "_initialized",
                "type": "t_uint64",
                "src": "@openzeppelin\\contracts-upgradeable\\proxy\\utils\\Initializable.sol:69",
                "offset": 0,
                "slot": "0"
              },
              {
                "contract": "Initializable",
                "label": "_initializing",
                "type": "t_bool",
                "src": "@openzeppelin\\contracts-upgradeable\\proxy\\utils\\Initializable.sol:73",
                "offset": 8,
                "slot": "0"
              }
            ]
          }
        },
        "solcVersion": "0.8.28"
      },
      "@openzeppelin/contracts-upgradeable/token/ERC20/ERC20Upgradeable.sol:ERC20Upgradeable": {
        "src": "@openzeppelin\\contracts-upgradeable\\token\\ERC20\\ERC20Upgradeable.sol:30",
        "inherit": [
          "@openzeppelin/contracts/interfaces/draft-IERC6093.sol:IERC20Errors",
          "@openzeppelin/contracts/token/ERC20/extensions/IERC20Metadata.sol:IERC20Metadata",
          "@openzeppelin/contracts/token/ERC20/IERC20.sol:IERC20",
          "@openzeppelin/contracts-upgradeable/utils/ContextUpgradeable.sol:ContextUpgradeable",
          "@openzeppelin/contracts-upgradeable/proxy/utils/Initializable.sol:Initializable"
        ],
        "libraries": [],
        "methods": [
          "name()",
          "symbol()",
          "decimals()",
          "totalSupply()",
          "balanceOf(address)",
          "transfer(address,uint256)",
          "allowance(address,address)",
          "approve(address,uint256)",
          "transferFrom(address,address,uint256)"
        ],
        "linkReferences": [],
        "errors": [],
        "layout": {
          "storage": [],
          "types": {
            "t_address": {
              "label": "address",
              "numberOfBytes": "20"
            },
            "t_bool": {
              "label": "bool",
              "numberOfBytes": "1"
            },
            "t_mapping(t_address,t_mapping(t_address,t_uint256))": {
              "label": "mapping(address => mapping(address => uint256))",
              "numberOfBytes": "32"
            },
            "t_mapping(t_address,t_uint256)": {
              "label": "mapping(address => uint256)",
              "numberOfBytes": "32"
            },
            "t_string_storage": {
              "label": "string",
              "numberOfBytes": "32"
            },
            "t_struct(ERC20Storage)222_storage": {
              "label": "struct ERC20Upgradeable.ERC20Storage",
              "members": [
                {
                  "label": "_balances",
                  "type": "t_mapping(t_address,t_uint256)",
                  "offset": 0,
                  "slot": "0"
                },
                {
                  "label": "_allowances",
                  "type": "t_mapping(t_address,t_mapping(t_address,t_uint256))",
                  "offset": 0,
                  "slot": "1"
                },
                {
                  "label": "_totalSupply",
                  "type": "t_uint256",
                  "offset": 0,
                  "slot": "2"
                },
                {
                  "label": "_name",
                  "type": "t_string_storage",
                  "offset": 0,
                  "slot": "3"
                },
                {
                  "label": "_symbol",
                  "type": "t_string_storage",
                  "offset": 0,
                  "slot": "4"
                }
              ],
              "numberOfBytes": "160"
            },
            "t_struct(InitializableStorage)73_storage": {
              "label": "struct Initializable.InitializableStorage",
              "members": [
                {
                  "label": "_initialized",
                  "type": "t_uint64",
                  "offset": 0,
                  "slot": "0"
                },
                {
                  "label": "_initializing",
                  "type": "t_bool",
                  "offset": 8,
                  "slot": "0"
                }
              ],
              "numberOfBytes": "32"
            },
            "t_uint256": {
              "label": "uint256",
              "numberOfBytes": "32"
            },
            "t_uint64": {
              "label": "uint64",
              "numberOfBytes": "8"
            }
          },
          "layoutVersion": "1.2",
          "flat": false,
          "namespaces": {
            "erc7201:openzeppelin.storage.ERC20": [
              {
                "contract": "ERC20Upgradeable",
                "label": "_balances",
                "type": "t_mapping(t_address,t_uint256)",
                "src": "@openzeppelin\\contracts-upgradeable\\token\\ERC20\\ERC20Upgradeable.sol:33",
                "offset": 0,
                "slot": "0"
              },
              {
                "contract": "ERC20Upgradeable",
                "label": "_allowances",
                "type": "t_mapping(t_address,t_mapping(t_address,t_uint256))",
                "src": "@openzeppelin\\contracts-upgradeable\\token\\ERC20\\ERC20Upgradeable.sol:35",
                "offset": 0,
                "slot": "1"
              },
              {
                "contract": "ERC20Upgradeable",
                "label": "_totalSupply",
                "type": "t_uint256",
                "src": "@openzeppelin\\contracts-upgradeable\\token\\ERC20\\ERC20Upgradeable.sol:37",
                "offset": 0,
                "slot": "2"
              },
              {
                "contract": "ERC20Upgradeable",
                "label": "_name",
                "type": "t_string_storage",
                "src": "@openzeppelin\\contracts-upgradeable\\token\\ERC20\\ERC20Upgradeable.sol:39",
                "offset": 0,
                "slot": "3"
              },
              {
                "contract": "ERC20Upgradeable",
                "label": "_symbol",
                "type": "t_string_storage",
                "src": "@openzeppelin\\contracts-upgradeable\\token\\ERC20\\ERC20Upgradeable.sol:40",
                "offset": 0,
                "slot": "4"
              }
            ],
            "erc7201:openzeppelin.storage.Initializable": [
              {
                "contract": "Initializable",
                "label": "_initialized",
                "type": "t_uint64",
                "src": "@openzeppelin\\contracts-upgradeable\\proxy\\utils\\Initializable.sol:69",
                "offset": 0,
                "slot": "0"
              },
              {
                "contract": "Initializable",
                "label": "_initializing",
                "type": "t_bool",
                "src": "@openzeppelin\\contracts-upgradeable\\proxy\\utils\\Initializable.sol:73",
                "offset": 8,
                "slot": "0"
              }
            ]
          }
        },
        "solcVersion": "0.8.28"
      },
      "@openzeppelin/contracts-upgradeable/token/ERC20/extensions/ERC20BurnableUpgradeable.sol:ERC20BurnableUpgradeable": {
        "src": "@openzeppelin\\contracts-upgradeable\\token\\ERC20\\extensions\\ERC20BurnableUpgradeable.sol:15",
        "inherit": [
          "@openzeppelin/contracts-upgradeable/token/ERC20/ERC20Upgradeable.sol:ERC20Upgradeable",
          "@openzeppelin/contracts/interfaces/draft-IERC6093.sol:IERC20Errors",
          "@openzeppelin/contracts/token/ERC20/extensions/IERC20Metadata.sol:IERC20Metadata",
          "@openzeppelin/contracts/token/ERC20/IERC20.sol:IERC20",
          "@openzeppelin/contracts-upgradeable/utils/ContextUpgradeable.sol:ContextUpgradeable",
          "@openzeppelin/contracts-upgradeable/proxy/utils/Initializable.sol:Initializable"
        ],
        "libraries": [],
        "methods": [
          "burn(uint256)",
          "burnFrom(address,uint256)"
        ],
        "linkReferences": [],
        "errors": [],
        "layout": {
          "storage": [],
          "types": {
            "t_address": {
              "label": "address",
              "numberOfBytes": "20"
            },
            "t_bool": {
              "label": "bool",
              "numberOfBytes": "1"
            },
            "t_mapping(t_address,t_mapping(t_address,t_uint256))": {
              "label": "mapping(address => mapping(address => uint256))",
              "numberOfBytes": "32"
            },
            "t_mapping(t_address,t_uint256)": {
              "label": "mapping(address => uint256)",
              "numberOfBytes": "32"
            },
            "t_string_storage": {
              "label": "string",
              "numberOfBytes": "32"
            },
            "t_struct(ERC20Storage)222_storage": {
              "label": "struct ERC20Upgradeable.ERC20Storage",
              "members": [
                {
                  "label": "_balances",
                  "type": "t_mapping(t_address,t_uint256)",
                  "offset": 0,
                  "slot": "0"
                },
                {
                  "label": "_allowances",
                  "type": "t_mapping(t_address,t_mapping(t_address,t_uint256))",
                  "offset": 0,
                  "slot": "1"
                },
                {
                  "label": "_totalSupply",
                  "type": "t_uint256",
                  "offset": 0,
                  "slot": "2"
                },
                {
                  "label": "_name",
                  "type": "t_string_storage",
                  "offset": 0,
                  "slot": "3"
                },
                {
                  "label": "_symbol",
                  "type": "t_string_storage",
                  "offset": 0,
                  "slot": "4"
                }
              ],
              "numberOfBytes": "160"
            },
            "t_struct(InitializableStorage)73_storage": {
              "label": "struct Initializable.InitializableStorage",
              "members": [
                {
                  "label": "_initialized",
                  "type": "t_uint64",
                  "offset": 0,
                  "slot": "0"
                },
                {
                  "label": "_initializing",
                  "type": "t_bool",
                  "offset": 8,
                  "slot": "0"
                }
              ],
              "numberOfBytes": "32"
            },
            "t_uint256": {
              "label": "uint256",
              "numberOfBytes": "32"
            },
            "t_uint64": {
              "label": "uint64",
              "numberOfBytes": "8"
            }
          },
          "layoutVersion": "1.2",
          "flat": false,
          "namespaces": {
            "erc7201:openzeppelin.storage.ERC20": [
              {
                "contract": "ERC20Upgradeable",
                "label": "_balances",
                "type": "t_mapping(t_address,t_uint256)",
                "src": "@openzeppelin\\contracts-upgradeable\\token\\ERC20\\ERC20Upgradeable.sol:33",
                "offset": 0,
                "slot": "0"
              },
              {
                "contract": "ERC20Upgradeable",
                "label": "_allowances",
                "type": "t_mapping(t_address,t_mapping(t_address,t_uint256))",
                "src": "@openzeppelin\\contracts-upgradeable\\token\\ERC20\\ERC20Upgradeable.sol:35",
                "offset": 0,
                "slot": "1"
              },
              {
                "contract": "ERC20Upgradeable",
                "label": "_totalSupply",
                "type": "t_uint256",
                "src": "@openzeppelin\\contracts-upgradeable\\token\\ERC20\\ERC20Upgradeable.sol:37",
                "offset": 0,
                "slot": "2"
              },
              {
                "contract": "ERC20Upgradeable",
                "label": "_name",
                "type": "t_string_storage",
                "src": "@openzeppelin\\contracts-upgradeable\\token\\ERC20\\ERC20Upgradeable.sol:39",
                "offset": 0,
                "slot": "3"
              },
              {
                "contract": "ERC20Upgradeable",
                "label": "_symbol",
                "type": "t_string_storage",
                "src": "@openzeppelin\\contracts-upgradeable\\token\\ERC20\\ERC20Upgradeable.sol:40",
                "offset": 0,
                "slot": "4"
              }
            ],
            "erc7201:openzeppelin.storage.Initializable": [
              {
                "contract": "Initializable",
                "label": "_initialized",
                "type": "t_uint64",
                "src": "@openzeppelin\\contracts-upgradeable\\proxy\\utils\\Initializable.sol:69",
                "offset": 0,
                "slot": "0"
              },
              {
                "contract": "Initializable",
                "label": "_initializing",
                "type": "t_bool",
                "src": "@openzeppelin\\contracts-upgradeable\\proxy\\utils\\Initializable.sol:73",
                "offset": 8,
                "slot": "0"
              }
            ]
          }
        },
        "solcVersion": "0.8.28"
      },
      "@openzeppelin/contracts-upgradeable/token/ERC20/extensions/ERC20PausableUpgradeable.sol:ERC20PausableUpgradeable": {
        "src": "@openzeppelin\\contracts-upgradeable\\token\\ERC20\\extensions\\ERC20PausableUpgradeable.sol:23",
        "inherit": [
          "@openzeppelin/contracts-upgradeable/utils/PausableUpgradeable.sol:PausableUpgradeable",
          "@openzeppelin/contracts-upgradeable/token/ERC20/ERC20Upgradeable.sol:ERC20Upgradeable",
          "@openzeppelin/contracts/interfaces/draft-IERC6093.sol:IERC20Errors",
          "@openzeppelin/contracts/token/ERC20/extensions/IERC20Metadata.sol:IERC20Metadata",
          "@openzeppelin/contracts/token/ERC20/IERC20.sol:IERC20",
          "@openzeppelin/contracts-upgradeable/utils/ContextUpgradeable.sol:ContextUpgradeable",
          "@openzeppelin/contracts-upgradeable/proxy/utils/Initializable.sol:Initializable"
        ],
        "libraries": [],
        "methods": [],
        "linkReferences": [],
        "errors": [],
        "layout": {
          "storage": [],
          "types": {
            "t_address": {
              "label": "address",
              "numberOfBytes": "20"
            },
            "t_bool": {
              "label": "bool",
              "numberOfBytes": "1"
            },
            "t_mapping(t_address,t_mapping(t_address,t_uint256))": {
              "label": "mapping(address => mapping(address => uint256))",
              "numberOfBytes": "32"
            },
            "t_mapping(t_address,t_uint256)": {
              "label": "mapping(address => uint256)",
              "numberOfBytes": "32"
            },
            "t_string_storage": {
              "label": "string",
              "numberOfBytes": "32"
            },
            "t_struct(ERC20Storage)222_storage": {
              "label": "struct ERC20Upgradeable.ERC20Storage",
              "members": [
                {
                  "label": "_balances",
                  "type": "t_mapping(t_address,t_uint256)",
                  "offset": 0,
                  "slot": "0"
                },
                {
                  "label": "_allowances",
                  "type": "t_mapping(t_address,t_mapping(t_address,t_uint256))",
                  "offset": 0,
                  "slot": "1"
                },
                {
                  "label": "_totalSupply",
                  "type": "t_uint256",
                  "offset": 0,
                  "slot": "2"
                },
                {
                  "label": "_name",
                  "type": "t_string_storage",
                  "offset": 0,
                  "slot": "3"
                },
                {
                  "label": "_symbol",
                  "type": "t_string_storage",
                  "offset": 0,
                  "slot": "4"
                }
              ],
              "numberOfBytes": "160"
            },
            "t_struct(InitializableStorage)73_storage": {
              "label": "struct Initializable.InitializableStorage",
              "members": [
                {
                  "label": "_initialized",
                  "type": "t_uint64",
                  "offset": 0,
                  "slot": "0"
                },
                {
                  "label": "_initializing",
                  "type": "t_bool",
                  "offset": 8,
                  "slot": "0"
                }
              ],
              "numberOfBytes": "32"
            },
            "t_struct(PausableStorage)611_storage": {
              "label": "struct PausableUpgradeable.PausableStorage",
              "members": [
                {
                  "label": "_paused",
                  "type": "t_bool",
                  "offset": 0,
                  "slot": "0"
                }
              ],
              "numberOfBytes": "32"
            },
            "t_uint256": {
              "label": "uint256",
              "numberOfBytes": "32"
            },
            "t_uint64": {
              "label": "uint64",
              "numberOfBytes": "8"
            }
          },
          "layoutVersion": "1.2",
          "flat": false,
          "namespaces": {
            "erc7201:openzeppelin.storage.Pausable": [
              {
                "contract": "PausableUpgradeable",
                "label": "_paused",
                "type": "t_bool",
                "src": "@openzeppelin\\contracts-upgradeable\\utils\\PausableUpgradeable.sol:21",
                "offset": 0,
                "slot": "0"
              }
            ],
            "erc7201:openzeppelin.storage.ERC20": [
              {
                "contract": "ERC20Upgradeable",
                "label": "_balances",
                "type": "t_mapping(t_address,t_uint256)",
                "src": "@openzeppelin\\contracts-upgradeable\\token\\ERC20\\ERC20Upgradeable.sol:33",
                "offset": 0,
                "slot": "0"
              },
              {
                "contract": "ERC20Upgradeable",
                "label": "_allowances",
                "type": "t_mapping(t_address,t_mapping(t_address,t_uint256))",
                "src": "@openzeppelin\\contracts-upgradeable\\token\\ERC20\\ERC20Upgradeable.sol:35",
                "offset": 0,
                "slot": "1"
              },
              {
                "contract": "ERC20Upgradeable",
                "label": "_totalSupply",
                "type": "t_uint256",
                "src": "@openzeppelin\\contracts-upgradeable\\token\\ERC20\\ERC20Upgradeable.sol:37",
                "offset": 0,
                "slot": "2"
              },
              {
                "contract": "ERC20Upgradeable",
                "label": "_name",
                "type": "t_string_storage",
                "src": "@openzeppelin\\contracts-upgradeable\\token\\ERC20\\ERC20Upgradeable.sol:39",
                "offset": 0,
                "slot": "3"
              },
              {
                "contract": "ERC20Upgradeable",
                "label": "_symbol",
                "type": "t_string_storage",
                "src": "@openzeppelin\\contracts-upgradeable\\token\\ERC20\\ERC20Upgradeable.sol:40",
                "offset": 0,
                "slot": "4"
              }
            ],
            "erc7201:openzeppelin.storage.Initializable": [
              {
                "contract": "Initializable",
                "label": "_initialized",
                "type": "t_uint64",
                "src": "@openzeppelin\\contracts-upgradeable\\proxy\\utils\\Initializable.sol:69",
                "offset": 0,
                "slot": "0"
              },
              {
                "contract": "Initializable",
                "label": "_initializing",
                "type": "t_bool",
                "src": "@openzeppelin\\contracts-upgradeable\\proxy\\utils\\Initializable.sol:73",
                "offset": 8,
                "slot": "0"
              }
            ]
          }
        },
        "solcVersion": "0.8.28"
      },
      "@openzeppelin/contracts-upgradeable/token/ERC20/extensions/ERC20PermitUpgradeable.sol:ERC20PermitUpgradeable": {
        "src": "@openzeppelin\\contracts-upgradeable\\token\\ERC20\\extensions\\ERC20PermitUpgradeable.sol:21",
        "inherit": [
          "@openzeppelin/contracts-upgradeable/utils/NoncesUpgradeable.sol:NoncesUpgradeable",
          "@openzeppelin/contracts-upgradeable/utils/cryptography/EIP712Upgradeable.sol:EIP712Upgradeable",
          "@openzeppelin/contracts/interfaces/IERC5267.sol:IERC5267",
          "@openzeppelin/contracts/token/ERC20/extensions/IERC20Permit.sol:IERC20Permit",
          "@openzeppelin/contracts-upgradeable/token/ERC20/ERC20Upgradeable.sol:ERC20Upgradeable",
          "@openzeppelin/contracts/interfaces/draft-IERC6093.sol:IERC20Errors",
          "@openzeppelin/contracts/token/ERC20/extensions/IERC20Metadata.sol:IERC20Metadata",
          "@openzeppelin/contracts/token/ERC20/IERC20.sol:IERC20",
          "@openzeppelin/contracts-upgradeable/utils/ContextUpgradeable.sol:ContextUpgradeable",
          "@openzeppelin/contracts-upgradeable/proxy/utils/Initializable.sol:Initializable"
        ],
        "libraries": [
          "@openzeppelin/contracts/utils/cryptography/ECDSA.sol:ECDSA"
        ],
        "methods": [
          "permit(address,address,uint256,uint256,uint8,bytes32,bytes32)",
          "nonces(address)",
          "DOMAIN_SEPARATOR()"
        ],
        "linkReferences": [],
        "errors": [],
        "layout": {
          "storage": [],
          "types": {
            "t_address": {
              "label": "address",
              "numberOfBytes": "20"
            },
            "t_bool": {
              "label": "bool",
              "numberOfBytes": "1"
            },
            "t_bytes32": {
              "label": "bytes32",
              "numberOfBytes": "32"
            },
            "t_mapping(t_address,t_mapping(t_address,t_uint256))": {
              "label": "mapping(address => mapping(address => uint256))",
              "numberOfBytes": "32"
            },
            "t_mapping(t_address,t_uint256)": {
              "label": "mapping(address => uint256)",
              "numberOfBytes": "32"
            },
            "t_string_storage": {
              "label": "string",
              "numberOfBytes": "32"
            },
            "t_struct(EIP712Storage)686_storage": {
              "label": "struct EIP712Upgradeable.EIP712Storage",
              "members": [
                {
                  "label": "_hashedName",
                  "type": "t_bytes32",
                  "offset": 0,
                  "slot": "0"
                },
                {
                  "label": "_hashedVersion",
                  "type": "t_bytes32",
                  "offset": 0,
                  "slot": "1"
                },
                {
                  "label": "_name",
                  "type": "t_string_storage",
                  "offset": 0,
                  "slot": "2"
                },
                {
                  "label": "_version",
                  "type": "t_string_storage",
                  "offset": 0,
                  "slot": "3"
                }
              ],
              "numberOfBytes": "128"
            },
            "t_struct(ERC20Storage)222_storage": {
              "label": "struct ERC20Upgradeable.ERC20Storage",
              "members": [
                {
                  "label": "_balances",
                  "type": "t_mapping(t_address,t_uint256)",
                  "offset": 0,
                  "slot": "0"
                },
                {
                  "label": "_allowances",
                  "type": "t_mapping(t_address,t_mapping(t_address,t_uint256))",
                  "offset": 0,
                  "slot": "1"
                },
                {
                  "label": "_totalSupply",
                  "type": "t_uint256",
                  "offset": 0,
                  "slot": "2"
                },
                {
                  "label": "_name",
                  "type": "t_string_storage",
                  "offset": 0,
                  "slot": "3"
                },
                {
                  "label": "_symbol",
                  "type": "t_string_storage",
                  "offset": 0,
                  "slot": "4"
                }
              ],
              "numberOfBytes": "160"
            },
            "t_struct(InitializableStorage)73_storage": {
              "label": "struct Initializable.InitializableStorage",
              "members": [
                {
                  "label": "_initialized",
                  "type": "t_uint64",
                  "offset": 0,
                  "slot": "0"
                },
                {
                  "label": "_initializing",
                  "type": "t_bool",
                  "offset": 8,
                  "slot": "0"
                }
              ],
              "numberOfBytes": "32"
            },
            "t_struct(NoncesStorage)557_storage": {
              "label": "struct NoncesUpgradeable.NoncesStorage",
              "members": [
                {
                  "label": "_nonces",
                  "type": "t_mapping(t_address,t_uint256)",
                  "offset": 0,
                  "slot": "0"
                }
              ],
              "numberOfBytes": "32"
            },
            "t_uint256": {
              "label": "uint256",
              "numberOfBytes": "32"
            },
            "t_uint64": {
              "label": "uint64",
              "numberOfBytes": "8"
            }
          },
          "layoutVersion": "1.2",
          "flat": false,
          "namespaces": {
            "erc7201:openzeppelin.storage.Nonces": [
              {
                "contract": "NoncesUpgradeable",
                "label": "_nonces",
                "type": "t_mapping(t_address,t_uint256)",
                "src": "@openzeppelin\\contracts-upgradeable\\utils\\NoncesUpgradeable.sol:17",
                "offset": 0,
                "slot": "0"
              }
            ],
            "erc7201:openzeppelin.storage.EIP712": [
              {
                "contract": "EIP712Upgradeable",
                "label": "_hashedName",
                "type": "t_bytes32",
                "src": "@openzeppelin\\contracts-upgradeable\\utils\\cryptography\\EIP712Upgradeable.sol:38",
                "offset": 0,
                "slot": "0"
              },
              {
                "contract": "EIP712Upgradeable",
                "label": "_hashedVersion",
                "type": "t_bytes32",
                "src": "@openzeppelin\\contracts-upgradeable\\utils\\cryptography\\EIP712Upgradeable.sol:40",
                "offset": 0,
                "slot": "1"
              },
              {
                "contract": "EIP712Upgradeable",
                "label": "_name",
                "type": "t_string_storage",
                "src": "@openzeppelin\\contracts-upgradeable\\utils\\cryptography\\EIP712Upgradeable.sol:42",
                "offset": 0,
                "slot": "2"
              },
              {
                "contract": "EIP712Upgradeable",
                "label": "_version",
                "type": "t_string_storage",
                "src": "@openzeppelin\\contracts-upgradeable\\utils\\cryptography\\EIP712Upgradeable.sol:43",
                "offset": 0,
                "slot": "3"
              }
            ],
            "erc7201:openzeppelin.storage.ERC20": [
              {
                "contract": "ERC20Upgradeable",
                "label": "_balances",
                "type": "t_mapping(t_address,t_uint256)",
                "src": "@openzeppelin\\contracts-upgradeable\\token\\ERC20\\ERC20Upgradeable.sol:33",
                "offset": 0,
                "slot": "0"
              },
              {
                "contract": "ERC20Upgradeable",
                "label": "_allowances",
                "type": "t_mapping(t_address,t_mapping(t_address,t_uint256))",
                "src": "@openzeppelin\\contracts-upgradeable\\token\\ERC20\\ERC20Upgradeable.sol:35",
                "offset": 0,
                "slot": "1"
              },
              {
                "contract": "ERC20Upgradeable",
                "label": "_totalSupply",
                "type": "t_uint256",
                "src": "@openzeppelin\\contracts-upgradeable\\token\\ERC20\\ERC20Upgradeable.sol:37",
                "offset": 0,
                "slot": "2"
              },
              {
                "contract": "ERC20Upgradeable",
                "label": "_name",
                "type": "t_string_storage",
                "src": "@openzeppelin\\contracts-upgradeable\\token\\ERC20\\ERC20Upgradeable.sol:39",
                "offset": 0,
                "slot": "3"
              },
              {
                "contract": "ERC20Upgradeable",
                "label": "_symbol",
                "type": "t_string_storage",
                "src": "@openzeppelin\\contracts-upgradeable\\token\\ERC20\\ERC20Upgradeable.sol:40",
                "offset": 0,
                "slot": "4"
              }
            ],
            "erc7201:openzeppelin.storage.Initializable": [
              {
                "contract": "Initializable",
                "label": "_initialized",
                "type": "t_uint64",
                "src": "@openzeppelin\\contracts-upgradeable\\proxy\\utils\\Initializable.sol:69",
                "offset": 0,
                "slot": "0"
              },
              {
                "contract": "Initializable",
                "label": "_initializing",
                "type": "t_bool",
                "src": "@openzeppelin\\contracts-upgradeable\\proxy\\utils\\Initializable.sol:73",
                "offset": 8,
                "slot": "0"
              }
            ]
          }
        },
        "solcVersion": "0.8.28"
      },
      "@openzeppelin/contracts-upgradeable/utils/ContextUpgradeable.sol:ContextUpgradeable": {
        "src": "@openzeppelin\\contracts-upgradeable\\utils\\ContextUpgradeable.sol:17",
        "inherit": [
          "@openzeppelin/contracts-upgradeable/proxy/utils/Initializable.sol:Initializable"
        ],
        "libraries": [],
        "methods": [],
        "linkReferences": [],
        "errors": [],
        "layout": {
          "storage": [],
          "types": {
            "t_bool": {
              "label": "bool",
              "numberOfBytes": "1"
            },
            "t_struct(InitializableStorage)73_storage": {
              "label": "struct Initializable.InitializableStorage",
              "members": [
                {
                  "label": "_initialized",
                  "type": "t_uint64",
                  "offset": 0,
                  "slot": "0"
                },
                {
                  "label": "_initializing",
                  "type": "t_bool",
                  "offset": 8,
                  "slot": "0"
                }
              ],
              "numberOfBytes": "32"
            },
            "t_uint64": {
              "label": "uint64",
              "numberOfBytes": "8"
            }
          },
          "layoutVersion": "1.2",
          "flat": false,
          "namespaces": {
            "erc7201:openzeppelin.storage.Initializable": [
              {
                "contract": "Initializable",
                "label": "_initialized",
                "type": "t_uint64",
                "src": "@openzeppelin\\contracts-upgradeable\\proxy\\utils\\Initializable.sol:69",
                "offset": 0,
                "slot": "0"
              },
              {
                "contract": "Initializable",
                "label": "_initializing",
                "type": "t_bool",
                "src": "@openzeppelin\\contracts-upgradeable\\proxy\\utils\\Initializable.sol:73",
                "offset": 8,
                "slot": "0"
              }
            ]
          }
        },
        "solcVersion": "0.8.28"
      },
      "@openzeppelin/contracts-upgradeable/utils/NoncesUpgradeable.sol:NoncesUpgradeable": {
        "src": "@openzeppelin\\contracts-upgradeable\\utils\\NoncesUpgradeable.sol:9",
        "inherit": [
          "@openzeppelin/contracts-upgradeable/proxy/utils/Initializable.sol:Initializable"
        ],
        "libraries": [],
        "methods": [
          "nonces(address)"
        ],
        "linkReferences": [],
        "errors": [],
        "layout": {
          "storage": [],
          "types": {
            "t_address": {
              "label": "address",
              "numberOfBytes": "20"
            },
            "t_bool": {
              "label": "bool",
              "numberOfBytes": "1"
            },
            "t_mapping(t_address,t_uint256)": {
              "label": "mapping(address => uint256)",
              "numberOfBytes": "32"
            },
            "t_struct(InitializableStorage)73_storage": {
              "label": "struct Initializable.InitializableStorage",
              "members": [
                {
                  "label": "_initialized",
                  "type": "t_uint64",
                  "offset": 0,
                  "slot": "0"
                },
                {
                  "label": "_initializing",
                  "type": "t_bool",
                  "offset": 8,
                  "slot": "0"
                }
              ],
              "numberOfBytes": "32"
            },
            "t_struct(NoncesStorage)557_storage": {
              "label": "struct NoncesUpgradeable.NoncesStorage",
              "members": [
                {
                  "label": "_nonces",
                  "type": "t_mapping(t_address,t_uint256)",
                  "offset": 0,
                  "slot": "0"
                }
              ],
              "numberOfBytes": "32"
            },
            "t_uint256": {
              "label": "uint256",
              "numberOfBytes": "32"
            },
            "t_uint64": {
              "label": "uint64",
              "numberOfBytes": "8"
            }
          },
          "layoutVersion": "1.2",
          "flat": false,
          "namespaces": {
            "erc7201:openzeppelin.storage.Nonces": [
              {
                "contract": "NoncesUpgradeable",
                "label": "_nonces",
                "type": "t_mapping(t_address,t_uint256)",
                "src": "@openzeppelin\\contracts-upgradeable\\utils\\NoncesUpgradeable.sol:17",
                "offset": 0,
                "slot": "0"
              }
            ],
            "erc7201:openzeppelin.storage.Initializable": [
              {
                "contract": "Initializable",
                "label": "_initialized",
                "type": "t_uint64",
                "src": "@openzeppelin\\contracts-upgradeable\\proxy\\utils\\Initializable.sol:69",
                "offset": 0,
                "slot": "0"
              },
              {
                "contract": "Initializable",
                "label": "_initializing",
                "type": "t_bool",
                "src": "@openzeppelin\\contracts-upgradeable\\proxy\\utils\\Initializable.sol:73",
                "offset": 8,
                "slot": "0"
              }
            ]
          }
        },
        "solcVersion": "0.8.28"
      },
      "@openzeppelin/contracts-upgradeable/utils/PausableUpgradeable.sol:PausableUpgradeable": {
        "src": "@openzeppelin\\contracts-upgradeable\\utils\\PausableUpgradeable.sol:18",
        "inherit": [
          "@openzeppelin/contracts-upgradeable/utils/ContextUpgradeable.sol:ContextUpgradeable",
          "@openzeppelin/contracts-upgradeable/proxy/utils/Initializable.sol:Initializable"
        ],
        "libraries": [],
        "methods": [
          "paused()"
        ],
        "linkReferences": [],
        "errors": [],
        "layout": {
          "storage": [],
          "types": {
            "t_bool": {
              "label": "bool",
              "numberOfBytes": "1"
            },
            "t_struct(InitializableStorage)73_storage": {
              "label": "struct Initializable.InitializableStorage",
              "members": [
                {
                  "label": "_initialized",
                  "type": "t_uint64",
                  "offset": 0,
                  "slot": "0"
                },
                {
                  "label": "_initializing",
                  "type": "t_bool",
                  "offset": 8,
                  "slot": "0"
                }
              ],
              "numberOfBytes": "32"
            },
            "t_struct(PausableStorage)611_storage": {
              "label": "struct PausableUpgradeable.PausableStorage",
              "members": [
                {
                  "label": "_paused",
                  "type": "t_bool",
                  "offset": 0,
                  "slot": "0"
                }
              ],
              "numberOfBytes": "32"
            },
            "t_uint64": {
              "label": "uint64",
              "numberOfBytes": "8"
            }
          },
          "layoutVersion": "1.2",
          "flat": false,
          "namespaces": {
            "erc7201:openzeppelin.storage.Pausable": [
              {
                "contract": "PausableUpgradeable",
                "label": "_paused",
                "type": "t_bool",
                "src": "@openzeppelin\\contracts-upgradeable\\utils\\PausableUpgradeable.sol:21",
                "offset": 0,
                "slot": "0"
              }
            ],
            "erc7201:openzeppelin.storage.Initializable": [
              {
                "contract": "Initializable",
                "label": "_initialized",
                "type": "t_uint64",
                "src": "@openzeppelin\\contracts-upgradeable\\proxy\\utils\\Initializable.sol:69",
                "offset": 0,
                "slot": "0"
              },
              {
                "contract": "Initializable",
                "label": "_initializing",
                "type": "t_bool",
                "src": "@openzeppelin\\contracts-upgradeable\\proxy\\utils\\Initializable.sol:73",
                "offset": 8,
                "slot": "0"
              }
            ]
          }
        },
        "solcVersion": "0.8.28"
      },
      "@openzeppelin/contracts-upgradeable/utils/cryptography/EIP712Upgradeable.sol:EIP712Upgradeable": {
        "src": "@openzeppelin\\contracts-upgradeable\\utils\\cryptography\\EIP712Upgradeable.sol:31",
        "inherit": [
          "@openzeppelin/contracts/interfaces/IERC5267.sol:IERC5267",
          "@openzeppelin/contracts-upgradeable/proxy/utils/Initializable.sol:Initializable"
        ],
        "libraries": [
          "@openzeppelin/contracts/utils/cryptography/MessageHashUtils.sol:MessageHashUtils"
        ],
        "methods": [
          "eip712Domain()"
        ],
        "linkReferences": [],
        "errors": [],
        "layout": {
          "storage": [],
          "types": {
            "t_bool": {
              "label": "bool",
              "numberOfBytes": "1"
            },
            "t_bytes32": {
              "label": "bytes32",
              "numberOfBytes": "32"
            },
            "t_string_storage": {
              "label": "string",
              "numberOfBytes": "32"
            },
            "t_struct(EIP712Storage)686_storage": {
              "label": "struct EIP712Upgradeable.EIP712Storage",
              "members": [
                {
                  "label": "_hashedName",
                  "type": "t_bytes32",
                  "offset": 0,
                  "slot": "0"
                },
                {
                  "label": "_hashedVersion",
                  "type": "t_bytes32",
                  "offset": 0,
                  "slot": "1"
                },
                {
                  "label": "_name",
                  "type": "t_string_storage",
                  "offset": 0,
                  "slot": "2"
                },
                {
                  "label": "_version",
                  "type": "t_string_storage",
                  "offset": 0,
                  "slot": "3"
                }
              ],
              "numberOfBytes": "128"
            },
            "t_struct(InitializableStorage)73_storage": {
              "label": "struct Initializable.InitializableStorage",
              "members": [
                {
                  "label": "_initialized",
                  "type": "t_uint64",
                  "offset": 0,
                  "slot": "0"
                },
                {
                  "label": "_initializing",
                  "type": "t_bool",
                  "offset": 8,
                  "slot": "0"
                }
              ],
              "numberOfBytes": "32"
            },
            "t_uint64": {
              "label": "uint64",
              "numberOfBytes": "8"
            }
          },
          "layoutVersion": "1.2",
          "flat": false,
          "namespaces": {
            "erc7201:openzeppelin.storage.EIP712": [
              {
                "contract": "EIP712Upgradeable",
                "label": "_hashedName",
                "type": "t_bytes32",
                "src": "@openzeppelin\\contracts-upgradeable\\utils\\cryptography\\EIP712Upgradeable.sol:38",
                "offset": 0,
                "slot": "0"
              },
              {
                "contract": "EIP712Upgradeable",
                "label": "_hashedVersion",
                "type": "t_bytes32",
                "src": "@openzeppelin\\contracts-upgradeable\\utils\\cryptography\\EIP712Upgradeable.sol:40",
                "offset": 0,
                "slot": "1"
              },
              {
                "contract": "EIP712Upgradeable",
                "label": "_name",
                "type": "t_string_storage",
                "src": "@openzeppelin\\contracts-upgradeable\\utils\\cryptography\\EIP712Upgradeable.sol:42",
                "offset": 0,
                "slot": "2"
              },
              {
                "contract": "EIP712Upgradeable",
                "label": "_version",
                "type": "t_string_storage",
                "src": "@openzeppelin\\contracts-upgradeable\\utils\\cryptography\\EIP712Upgradeable.sol:43",
                "offset": 0,
                "slot": "3"
              }
            ],
            "erc7201:openzeppelin.storage.Initializable": [
              {
                "contract": "Initializable",
                "label": "_initialized",
                "type": "t_uint64",
                "src": "@openzeppelin\\contracts-upgradeable\\proxy\\utils\\Initializable.sol:69",
                "offset": 0,
                "slot": "0"
              },
              {
                "contract": "Initializable",
                "label": "_initializing",
                "type": "t_bool",
                "src": "@openzeppelin\\contracts-upgradeable\\proxy\\utils\\Initializable.sol:73",
                "offset": 8,
                "slot": "0"
              }
            ]
          }
        },
        "solcVersion": "0.8.28"
      },
      "@openzeppelin/contracts/interfaces/IERC1967.sol:IERC1967": {
        "src": "@openzeppelin\\contracts\\interfaces\\IERC1967.sol:9",
        "inherit": [],
        "libraries": [],
        "methods": [],
        "linkReferences": [],
        "errors": [],
        "layout": {
          "storage": [],
          "types": {},
          "layoutVersion": "1.2",
          "flat": false,
          "namespaces": {}
        },
        "solcVersion": "0.8.28"
      },
      "@openzeppelin/contracts/interfaces/IERC5267.sol:IERC5267": {
        "src": "@openzeppelin\\contracts\\interfaces\\IERC5267.sol:6",
        "inherit": [],
        "libraries": [],
        "methods": [
          "eip712Domain()"
        ],
        "linkReferences": [],
        "errors": [],
        "layout": {
          "storage": [],
          "types": {},
          "layoutVersion": "1.2",
          "flat": false,
          "namespaces": {}
        },
        "solcVersion": "0.8.28"
      },
      "@openzeppelin/contracts/interfaces/draft-IERC1822.sol:IERC1822Proxiable": {
        "src": "@openzeppelin\\contracts\\interfaces\\draft-IERC1822.sol:10",
        "inherit": [],
        "libraries": [],
        "methods": [
          "proxiableUUID()"
        ],
        "linkReferences": [],
        "errors": [],
        "layout": {
          "storage": [],
          "types": {},
          "layoutVersion": "1.2",
          "flat": false,
          "namespaces": {}
        },
        "solcVersion": "0.8.28"
      },
      "@openzeppelin/contracts/interfaces/draft-IERC6093.sol:IERC1155Errors": {
        "src": "@openzeppelin\\contracts\\interfaces\\draft-IERC6093.sol:113",
        "inherit": [],
        "libraries": [],
        "methods": [],
        "linkReferences": [],
        "errors": [],
        "layout": {
          "storage": [],
          "types": {},
          "layoutVersion": "1.2",
          "flat": false,
          "namespaces": {}
        },
        "solcVersion": "0.8.28"
      },
      "@openzeppelin/contracts/interfaces/draft-IERC6093.sol:IERC20Errors": {
        "src": "@openzeppelin\\contracts\\interfaces\\draft-IERC6093.sol:9",
        "inherit": [],
        "libraries": [],
        "methods": [],
        "linkReferences": [],
        "errors": [],
        "layout": {
          "storage": [],
          "types": {},
          "layoutVersion": "1.2",
          "flat": false,
          "namespaces": {}
        },
        "solcVersion": "0.8.28"
      },
      "@openzeppelin/contracts/interfaces/draft-IERC6093.sol:IERC721Errors": {
        "src": "@openzeppelin\\contracts\\interfaces\\draft-IERC6093.sol:55",
        "inherit": [],
        "libraries": [],
        "methods": [],
        "linkReferences": [],
        "errors": [],
        "layout": {
          "storage": [],
          "types": {},
          "layoutVersion": "1.2",
          "flat": false,
          "namespaces": {}
        },
        "solcVersion": "0.8.28"
      },
      "@openzeppelin/contracts/proxy/ERC1967/ERC1967Utils.sol:ERC1967Utils": {
        "src": "@openzeppelin\\contracts\\proxy\\ERC1967\\ERC1967Utils.sol:15",
        "version": {
          "withMetadata": "8922c5f57ce663954997f6d9c2e516ca0d953582f5c733246b9a1f52f331ef14",
          "withoutMetadata": "a64c6cf9c6ba9368f5132c93a0196b3204a7963dbb4dd05dfddb4ab23126b8db",
          "linkedWithoutMetadata": "a64c6cf9c6ba9368f5132c93a0196b3204a7963dbb4dd05dfddb4ab23126b8db"
        },
        "inherit": [],
        "libraries": [
          "@openzeppelin/contracts/utils/StorageSlot.sol:StorageSlot",
          "@openzeppelin/contracts/utils/Address.sol:Address"
        ],
        "methods": [],
        "linkReferences": [],
        "errors": [
          {
            "kind": "delegatecall",
            "src": "@openzeppelin\\contracts\\utils\\Address.sol:97"
          },
          {
            "kind": "delegatecall",
            "src": "@openzeppelin\\contracts\\utils\\Address.sol:97"
          }
        ],
        "layout": {
          "storage": [],
          "types": {},
          "layoutVersion": "1.2",
          "flat": false,
          "namespaces": {}
        },
        "solcVersion": "0.8.28"
      },
      "@openzeppelin/contracts/proxy/beacon/IBeacon.sol:IBeacon": {
        "src": "@openzeppelin\\contracts\\proxy\\beacon\\IBeacon.sol:9",
        "inherit": [],
        "libraries": [],
        "methods": [
          "implementation()"
        ],
        "linkReferences": [],
        "errors": [],
        "layout": {
          "storage": [],
          "types": {},
          "layoutVersion": "1.2",
          "flat": false,
          "namespaces": {}
        },
        "solcVersion": "0.8.28"
      },
      "@openzeppelin/contracts/token/ERC20/IERC20.sol:IERC20": {
        "src": "@openzeppelin\\contracts\\token\\ERC20\\IERC20.sol:9",
        "inherit": [],
        "libraries": [],
        "methods": [
          "totalSupply()",
          "balanceOf(address)",
          "transfer(address,uint256)",
          "allowance(address,address)",
          "approve(address,uint256)",
          "transferFrom(address,address,uint256)"
        ],
        "linkReferences": [],
        "errors": [],
        "layout": {
          "storage": [],
          "types": {},
          "layoutVersion": "1.2",
          "flat": false,
          "namespaces": {}
        },
        "solcVersion": "0.8.28"
      },
      "@openzeppelin/contracts/token/ERC20/extensions/IERC20Metadata.sol:IERC20Metadata": {
        "src": "@openzeppelin\\contracts\\token\\ERC20\\extensions\\IERC20Metadata.sol:11",
        "inherit": [
          "@openzeppelin/contracts/token/ERC20/IERC20.sol:IERC20"
        ],
        "libraries": [],
        "methods": [
          "name()",
          "symbol()",
          "decimals()"
        ],
        "linkReferences": [],
        "errors": [],
        "layout": {
          "storage": [],
          "types": {},
          "layoutVersion": "1.2",
          "flat": false,
          "namespaces": {}
        },
        "solcVersion": "0.8.28"
      },
      "@openzeppelin/contracts/token/ERC20/extensions/IERC20Permit.sol:IERC20Permit": {
        "src": "@openzeppelin\\contracts\\token\\ERC20\\extensions\\IERC20Permit.sol:42",
        "inherit": [],
        "libraries": [],
        "methods": [
          "permit(address,address,uint256,uint256,uint8,bytes32,bytes32)",
          "nonces(address)",
          "DOMAIN_SEPARATOR()"
        ],
        "linkReferences": [],
        "errors": [],
        "layout": {
          "storage": [],
          "types": {},
          "layoutVersion": "1.2",
          "flat": false,
          "namespaces": {}
        },
        "solcVersion": "0.8.28"
      },
      "@openzeppelin/contracts/utils/Address.sol:Address": {
        "src": "@openzeppelin\\contracts\\utils\\Address.sol:11",
        "version": {
          "withMetadata": "ed054ce2c98513130389087d2d590ee8417a9a8ac31e8eb102a32b183a2a62c3",
          "withoutMetadata": "a64c6cf9c6ba9368f5132c93a0196b3204a7963dbb4dd05dfddb4ab23126b8db",
          "linkedWithoutMetadata": "a64c6cf9c6ba9368f5132c93a0196b3204a7963dbb4dd05dfddb4ab23126b8db"
        },
        "inherit": [],
        "libraries": [
          "@openzeppelin/contracts/utils/Errors.sol:Errors"
        ],
        "methods": [],
        "linkReferences": [],
        "errors": [
          {
            "kind": "delegatecall",
            "src": "@openzeppelin\\contracts\\utils\\Address.sol:97"
          }
        ],
        "layout": {
          "storage": [],
          "types": {},
          "layoutVersion": "1.2",
          "flat": false,
          "namespaces": {}
        },
        "solcVersion": "0.8.28"
      },
      "@openzeppelin/contracts/utils/Errors.sol:Errors": {
        "src": "@openzeppelin\\contracts\\utils\\Errors.sol:14",
        "version": {
          "withMetadata": "f4274fbf3d6c2176ae1e148ca1fd3dfab68a3b73bfcb548e61464f49be6c8d86",
          "withoutMetadata": "a64c6cf9c6ba9368f5132c93a0196b3204a7963dbb4dd05dfddb4ab23126b8db",
          "linkedWithoutMetadata": "a64c6cf9c6ba9368f5132c93a0196b3204a7963dbb4dd05dfddb4ab23126b8db"
        },
        "inherit": [],
        "libraries": [],
        "methods": [],
        "linkReferences": [],
        "errors": [],
        "layout": {
          "storage": [],
          "types": {},
          "layoutVersion": "1.2",
          "flat": false,
          "namespaces": {}
        },
        "solcVersion": "0.8.28"
      },
      "@openzeppelin/contracts/utils/Panic.sol:Panic": {
        "src": "@openzeppelin\\contracts\\utils\\Panic.sol:26",
        "version": {
          "withMetadata": "18af38b215aa82e5b9e190077fe255402503dd79151eff9011a50d73506f48c6",
          "withoutMetadata": "a64c6cf9c6ba9368f5132c93a0196b3204a7963dbb4dd05dfddb4ab23126b8db",
          "linkedWithoutMetadata": "a64c6cf9c6ba9368f5132c93a0196b3204a7963dbb4dd05dfddb4ab23126b8db"
        },
        "inherit": [],
        "libraries": [],
        "methods": [],
        "linkReferences": [],
        "errors": [],
        "layout": {
          "storage": [],
          "types": {},
          "layoutVersion": "1.2",
          "flat": false,
          "namespaces": {}
        },
        "solcVersion": "0.8.28"
      },
      "@openzeppelin/contracts/utils/StorageSlot.sol:StorageSlot": {
        "src": "@openzeppelin\\contracts\\utils\\StorageSlot.sol:34",
        "version": {
          "withMetadata": "0a220b1eaa74f4801b4218f9511ce9227040f319bc016a31b823b4f741e3f229",
          "withoutMetadata": "a64c6cf9c6ba9368f5132c93a0196b3204a7963dbb4dd05dfddb4ab23126b8db",
          "linkedWithoutMetadata": "a64c6cf9c6ba9368f5132c93a0196b3204a7963dbb4dd05dfddb4ab23126b8db"
        },
        "inherit": [],
        "libraries": [],
        "methods": [],
        "linkReferences": [],
        "errors": [],
        "layout": {
          "storage": [],
          "types": {},
          "layoutVersion": "1.2",
          "flat": false,
          "namespaces": {}
        },
        "solcVersion": "0.8.28"
      },
      "@openzeppelin/contracts/utils/Strings.sol:Strings": {
        "src": "@openzeppelin\\contracts\\utils\\Strings.sol:13",
        "version": {
          "withMetadata": "636fbc46041ea30270d2e368f85d6081990c0eb18aeb84ebbb140292788847b9",
          "withoutMetadata": "a64c6cf9c6ba9368f5132c93a0196b3204a7963dbb4dd05dfddb4ab23126b8db",
          "linkedWithoutMetadata": "a64c6cf9c6ba9368f5132c93a0196b3204a7963dbb4dd05dfddb4ab23126b8db"
        },
        "inherit": [],
        "libraries": [
          "@openzeppelin/contracts/utils/math/SafeCast.sol:SafeCast",
          "@openzeppelin/contracts/utils/math/Math.sol:Math",
          "@openzeppelin/contracts/utils/math/SignedMath.sol:SignedMath"
        ],
        "methods": [],
        "linkReferences": [],
        "errors": [],
        "layout": {
          "storage": [],
          "types": {},
          "layoutVersion": "1.2",
          "flat": false,
          "namespaces": {}
        },
        "solcVersion": "0.8.28"
      },
      "@openzeppelin/contracts/utils/cryptography/ECDSA.sol:ECDSA": {
        "src": "@openzeppelin\\contracts\\utils\\cryptography\\ECDSA.sol:12",
        "version": {
          "withMetadata": "346ea109f36dca71dea73a4a536204c780f04372a3d0c54d9c6d5391aa8fe850",
          "withoutMetadata": "a64c6cf9c6ba9368f5132c93a0196b3204a7963dbb4dd05dfddb4ab23126b8db",
          "linkedWithoutMetadata": "a64c6cf9c6ba9368f5132c93a0196b3204a7963dbb4dd05dfddb4ab23126b8db"
        },
        "inherit": [],
        "libraries": [],
        "methods": [],
        "linkReferences": [],
        "errors": [],
        "layout": {
          "storage": [],
          "types": {},
          "layoutVersion": "1.2",
          "flat": false,
          "namespaces": {}
        },
        "solcVersion": "0.8.28"
      },
      "@openzeppelin/contracts/utils/cryptography/MessageHashUtils.sol:MessageHashUtils": {
        "src": "@openzeppelin\\contracts\\utils\\cryptography\\MessageHashUtils.sol:15",
        "version": {
          "withMetadata": "de32c51ec8c96a966d369c0a310130c5e2b13f0354ca73d1cb7c0da531cd4592",
          "withoutMetadata": "a64c6cf9c6ba9368f5132c93a0196b3204a7963dbb4dd05dfddb4ab23126b8db",
          "linkedWithoutMetadata": "a64c6cf9c6ba9368f5132c93a0196b3204a7963dbb4dd05dfddb4ab23126b8db"
        },
        "inherit": [],
        "libraries": [
          "@openzeppelin/contracts/utils/Strings.sol:Strings"
        ],
        "methods": [],
        "linkReferences": [],
        "errors": [],
        "layout": {
          "storage": [],
          "types": {},
          "layoutVersion": "1.2",
          "flat": false,
          "namespaces": {}
        },
        "solcVersion": "0.8.28"
      },
      "@openzeppelin/contracts/utils/math/Math.sol:Math": {
        "src": "@openzeppelin\\contracts\\utils\\math\\Math.sol:12",
        "version": {
          "withMetadata": "d615bafc54e27f9ceb506c0d3dcf5abffa16025fe133b89c97a02b4ce8ffe7f7",
          "withoutMetadata": "a64c6cf9c6ba9368f5132c93a0196b3204a7963dbb4dd05dfddb4ab23126b8db",
          "linkedWithoutMetadata": "a64c6cf9c6ba9368f5132c93a0196b3204a7963dbb4dd05dfddb4ab23126b8db"
        },
        "inherit": [],
        "libraries": [
          "@openzeppelin/contracts/utils/math/SafeCast.sol:SafeCast",
          "@openzeppelin/contracts/utils/math/Math.sol:Math",
          "@openzeppelin/contracts/utils/Panic.sol:Panic"
        ],
        "methods": [],
        "linkReferences": [],
        "errors": [],
        "layout": {
          "storage": [],
          "types": {},
          "layoutVersion": "1.2",
          "flat": false,
          "namespaces": {}
        },
        "solcVersion": "0.8.28"
      },
      "@openzeppelin/contracts/utils/math/SafeCast.sol:SafeCast": {
        "src": "@openzeppelin\\contracts\\utils\\math\\SafeCast.sol:19",
        "version": {
          "withMetadata": "a7f1ca3b8aa423805776ae8f808db352566e4239432fa65596841d6263194dd0",
          "withoutMetadata": "a64c6cf9c6ba9368f5132c93a0196b3204a7963dbb4dd05dfddb4ab23126b8db",
          "linkedWithoutMetadata": "a64c6cf9c6ba9368f5132c93a0196b3204a7963dbb4dd05dfddb4ab23126b8db"
        },
        "inherit": [],
        "libraries": [],
        "methods": [],
        "linkReferences": [],
        "errors": [],
        "layout": {
          "storage": [],
          "types": {},
          "layoutVersion": "1.2",
          "flat": false,
          "namespaces": {}
        },
        "solcVersion": "0.8.28"
      },
      "@openzeppelin/contracts/utils/math/SignedMath.sol:SignedMath": {
        "src": "@openzeppelin\\contracts\\utils\\math\\SignedMath.sol:11",
        "version": {
          "withMetadata": "8f8d91cf5ee7bf61e273f61af3226f85a57f9f7d7a15676b74d5deda80d82371",
          "withoutMetadata": "a64c6cf9c6ba9368f5132c93a0196b3204a7963dbb4dd05dfddb4ab23126b8db",
          "linkedWithoutMetadata": "a64c6cf9c6ba9368f5132c93a0196b3204a7963dbb4dd05dfddb4ab23126b8db"
        },
        "inherit": [],
        "libraries": [
          "@openzeppelin/contracts/utils/math/SafeCast.sol:SafeCast"
        ],
        "methods": [],
        "linkReferences": [],
        "errors": [],
        "layout": {
          "storage": [],
          "types": {},
          "layoutVersion": "1.2",
          "flat": false,
          "namespaces": {}
        },
        "solcVersion": "0.8.28"
      },
      "contracts/FlameBornToken.sol:FlameBornToken": {
        "src": "contracts\\FlameBornToken.sol:17",
        "version": {
          "withMetadata": "6181031a367e795fef9c804c44583df85ae455502d8dfb61aeb421cccb07eb64",
          "withoutMetadata": "d3cc79ea4eb970f5e97964345fd382c19aeec5e0f4e58d84733c2a1842b62968",
          "linkedWithoutMetadata": "d3cc79ea4eb970f5e97964345fd382c19aeec5e0f4e58d84733c2a1842b62968"
        },
        "inherit": [
          "@openzeppelin/contracts-upgradeable/proxy/utils/UUPSUpgradeable.sol:UUPSUpgradeable",
          "@openzeppelin/contracts/interfaces/draft-IERC1822.sol:IERC1822Proxiable",
          "@openzeppelin/contracts-upgradeable/token/ERC20/extensions/ERC20PermitUpgradeable.sol:ERC20PermitUpgradeable",
          "@openzeppelin/contracts-upgradeable/utils/NoncesUpgradeable.sol:NoncesUpgradeable",
          "@openzeppelin/contracts-upgradeable/utils/cryptography/EIP712Upgradeable.sol:EIP712Upgradeable",
          "@openzeppelin/contracts/interfaces/IERC5267.sol:IERC5267",
          "@openzeppelin/contracts/token/ERC20/extensions/IERC20Permit.sol:IERC20Permit",
          "@openzeppelin/contracts-upgradeable/access/OwnableUpgradeable.sol:OwnableUpgradeable",
          "@openzeppelin/contracts-upgradeable/token/ERC20/extensions/ERC20PausableUpgradeable.sol:ERC20PausableUpgradeable",
          "@openzeppelin/contracts-upgradeable/utils/PausableUpgradeable.sol:PausableUpgradeable",
          "@openzeppelin/contracts-upgradeable/token/ERC20/extensions/ERC20BurnableUpgradeable.sol:ERC20BurnableUpgradeable",
          "@openzeppelin/contracts-upgradeable/token/ERC20/ERC20Upgradeable.sol:ERC20Upgradeable",
          "@openzeppelin/contracts/interfaces/draft-IERC6093.sol:IERC20Errors",
          "@openzeppelin/contracts/token/ERC20/extensions/IERC20Metadata.sol:IERC20Metadata",
          "@openzeppelin/contracts/token/ERC20/IERC20.sol:IERC20",
          "@openzeppelin/contracts-upgradeable/utils/ContextUpgradeable.sol:ContextUpgradeable",
          "@openzeppelin/contracts-upgradeable/proxy/utils/Initializable.sol:Initializable"
        ],
        "libraries": [],
        "methods": [
          "()",
          "initialize(address)",
          "pause()",
          "unpause()",
          "mint(address,uint256)"
        ],
        "linkReferences": [],
        "errors": [],
        "layout": {
          "storage": [],
          "types": {
            "t_address": {
              "label": "address",
              "numberOfBytes": "20"
            },
            "t_bool": {
              "label": "bool",
              "numberOfBytes": "1"
            },
            "t_bytes32": {
              "label": "bytes32",
              "numberOfBytes": "32"
            },
            "t_mapping(t_address,t_mapping(t_address,t_uint256))": {
              "label": "mapping(address => mapping(address => uint256))",
              "numberOfBytes": "32"
            },
            "t_mapping(t_address,t_uint256)": {
              "label": "mapping(address => uint256)",
              "numberOfBytes": "32"
            },
            "t_string_storage": {
              "label": "string",
              "numberOfBytes": "32"
            },
            "t_struct(EIP712Storage)686_storage": {
              "label": "struct EIP712Upgradeable.EIP712Storage",
              "members": [
                {
                  "label": "_hashedName",
                  "type": "t_bytes32",
                  "offset": 0,
                  "slot": "0"
                },
                {
                  "label": "_hashedVersion",
                  "type": "t_bytes32",
                  "offset": 0,
                  "slot": "1"
                },
                {
                  "label": "_name",
                  "type": "t_string_storage",
                  "offset": 0,
                  "slot": "2"
                },
                {
                  "label": "_version",
                  "type": "t_string_storage",
                  "offset": 0,
                  "slot": "3"
                }
              ],
              "numberOfBytes": "128"
            },
            "t_struct(ERC20Storage)222_storage": {
              "label": "struct ERC20Upgradeable.ERC20Storage",
              "members": [
                {
                  "label": "_balances",
                  "type": "t_mapping(t_address,t_uint256)",
                  "offset": 0,
                  "slot": "0"
                },
                {
                  "label": "_allowances",
                  "type": "t_mapping(t_address,t_mapping(t_address,t_uint256))",
                  "offset": 0,
                  "slot": "1"
                },
                {
                  "label": "_totalSupply",
                  "type": "t_uint256",
                  "offset": 0,
                  "slot": "2"
                },
                {
                  "label": "_name",
                  "type": "t_string_storage",
                  "offset": 0,
                  "slot": "3"
                },
                {
                  "label": "_symbol",
                  "type": "t_string_storage",
                  "offset": 0,
                  "slot": "4"
                }
              ],
              "numberOfBytes": "160"
            },
            "t_struct(InitializableStorage)73_storage": {
              "label": "struct Initializable.InitializableStorage",
              "members": [
                {
                  "label": "_initialized",
                  "type": "t_uint64",
                  "offset": 0,
                  "slot": "0"
                },
                {
                  "label": "_initializing",
                  "type": "t_bool",
                  "offset": 8,
                  "slot": "0"
                }
              ],
              "numberOfBytes": "32"
            },
            "t_struct(NoncesStorage)557_storage": {
              "label": "struct NoncesUpgradeable.NoncesStorage",
              "members": [
                {
                  "label": "_nonces",
                  "type": "t_mapping(t_address,t_uint256)",
                  "offset": 0,
                  "slot": "0"
                }
              ],
              "numberOfBytes": "32"
            },
            "t_struct(OwnableStorage)13_storage": {
              "label": "struct OwnableUpgradeable.OwnableStorage",
              "members": [
                {
                  "label": "_owner",
                  "type": "t_address",
                  "offset": 0,
                  "slot": "0"
                }
              ],
              "numberOfBytes": "32"
            },
            "t_struct(PausableStorage)611_storage": {
              "label": "struct PausableUpgradeable.PausableStorage",
              "members": [
                {
                  "label": "_paused",
                  "type": "t_bool",
                  "offset": 0,
                  "slot": "0"
                }
              ],
              "numberOfBytes": "32"
            },
            "t_uint256": {
              "label": "uint256",
              "numberOfBytes": "32"
            },
            "t_uint64": {
              "label": "uint64",
              "numberOfBytes": "8"
            }
          },
          "layoutVersion": "1.2",
          "flat": false,
          "namespaces": {
            "erc7201:openzeppelin.storage.Nonces": [
              {
                "contract": "NoncesUpgradeable",
                "label": "_nonces",
                "type": "t_mapping(t_address,t_uint256)",
                "src": "@openzeppelin\\contracts-upgradeable\\utils\\NoncesUpgradeable.sol:17",
                "offset": 0,
                "slot": "0"
              }
            ],
            "erc7201:openzeppelin.storage.EIP712": [
              {
                "contract": "EIP712Upgradeable",
                "label": "_hashedName",
                "type": "t_bytes32",
                "src": "@openzeppelin\\contracts-upgradeable\\utils\\cryptography\\EIP712Upgradeable.sol:38",
                "offset": 0,
                "slot": "0"
              },
              {
                "contract": "EIP712Upgradeable",
                "label": "_hashedVersion",
                "type": "t_bytes32",
                "src": "@openzeppelin\\contracts-upgradeable\\utils\\cryptography\\EIP712Upgradeable.sol:40",
                "offset": 0,
                "slot": "1"
              },
              {
                "contract": "EIP712Upgradeable",
                "label": "_name",
                "type": "t_string_storage",
                "src": "@openzeppelin\\contracts-upgradeable\\utils\\cryptography\\EIP712Upgradeable.sol:42",
                "offset": 0,
                "slot": "2"
              },
              {
                "contract": "EIP712Upgradeable",
                "label": "_version",
                "type": "t_string_storage",
                "src": "@openzeppelin\\contracts-upgradeable\\utils\\cryptography\\EIP712Upgradeable.sol:43",
                "offset": 0,
                "slot": "3"
              }
            ],
            "erc7201:openzeppelin.storage.Ownable": [
              {
                "contract": "OwnableUpgradeable",
                "label": "_owner",
                "type": "t_address",
                "src": "@openzeppelin\\contracts-upgradeable\\access\\OwnableUpgradeable.sol:24",
                "offset": 0,
                "slot": "0"
              }
            ],
            "erc7201:openzeppelin.storage.Pausable": [
              {
                "contract": "PausableUpgradeable",
                "label": "_paused",
                "type": "t_bool",
                "src": "@openzeppelin\\contracts-upgradeable\\utils\\PausableUpgradeable.sol:21",
                "offset": 0,
                "slot": "0"
              }
            ],
            "erc7201:openzeppelin.storage.ERC20": [
              {
                "contract": "ERC20Upgradeable",
                "label": "_balances",
                "type": "t_mapping(t_address,t_uint256)",
                "src": "@openzeppelin\\contracts-upgradeable\\token\\ERC20\\ERC20Upgradeable.sol:33",
                "offset": 0,
                "slot": "0"
              },
              {
                "contract": "ERC20Upgradeable",
                "label": "_allowances",
                "type": "t_mapping(t_address,t_mapping(t_address,t_uint256))",
                "src": "@openzeppelin\\contracts-upgradeable\\token\\ERC20\\ERC20Upgradeable.sol:35",
                "offset": 0,
                "slot": "1"
              },
              {
                "contract": "ERC20Upgradeable",
                "label": "_totalSupply",
                "type": "t_uint256",
                "src": "@openzeppelin\\contracts-upgradeable\\token\\ERC20\\ERC20Upgradeable.sol:37",
                "offset": 0,
                "slot": "2"
              },
              {
                "contract": "ERC20Upgradeable",
                "label": "_name",
                "type": "t_string_storage",
                "src": "@openzeppelin\\contracts-upgradeable\\token\\ERC20\\ERC20Upgradeable.sol:39",
                "offset": 0,
                "slot": "3"
              },
              {
                "contract": "ERC20Upgradeable",
                "label": "_symbol",
                "type": "t_string_storage",
                "src": "@openzeppelin\\contracts-upgradeable\\token\\ERC20\\ERC20Upgradeable.sol:40",
                "offset": 0,
                "slot": "4"
              }
            ],
            "erc7201:openzeppelin.storage.Initializable": [
              {
                "contract": "Initializable",
                "label": "_initialized",
                "type": "t_uint64",
                "src": "@openzeppelin\\contracts-upgradeable\\proxy\\utils\\Initializable.sol:69",
                "offset": 0,
                "slot": "0"
              },
              {
                "contract": "Initializable",
                "label": "_initializing",
                "type": "t_bool",
                "src": "@openzeppelin\\contracts-upgradeable\\proxy\\utils\\Initializable.sol:73",
                "offset": 8,
                "slot": "0"
              }
            ]
          }
        },
        "solcVersion": "0.8.28"
      },
      "contracts/Lock.sol:Lock": {
        "src": "contracts\\Lock.sol:7",
        "version": {
          "withMetadata": "905728a2297ea88b2fd2c1cd2e7cc2cc9eb84f8f1c8909f3ee7a5555eaee3367",
          "withoutMetadata": "58cefd5747baf40b25df55b33379d9ec089fad39f84bf91d803367d328ccdf29",
          "linkedWithoutMetadata": "58cefd5747baf40b25df55b33379d9ec089fad39f84bf91d803367d328ccdf29"
        },
        "inherit": [],
        "libraries": [],
        "methods": [
          "(uint256)",
          "withdraw()"
        ],
        "linkReferences": [],
        "errors": [
          {
            "kind": "constructor",
            "contract": "Lock",
            "src": "contracts\\Lock.sol:13"
          }
        ],
        "layout": {
          "storage": [
            {
              "label": "unlockTime",
              "offset": 0,
              "slot": "0",
              "type": "t_uint256",
              "contract": "Lock",
              "src": "contracts\\Lock.sol:8"
            },
            {
              "label": "owner",
              "offset": 0,
              "slot": "1",
              "type": "t_address_payable",
              "contract": "Lock",
              "src": "contracts\\Lock.sol:9"
            }
          ],
          "types": {
            "t_address_payable": {
              "label": "address payable",
              "numberOfBytes": "20"
            },
            "t_uint256": {
              "label": "uint256",
              "numberOfBytes": "32"
            }
          },
          "layoutVersion": "1.2",
          "flat": true,
          "namespaces": {}
        },
        "solcVersion": "0.8.28"
      }
    }
  ]
}